stamp/DataSet.py
stamp/Modules.py
stamp/STAMP.py
stamp/__init__.py
stamp/utils.py
stamp/version.py
cell_stamp-0.1.2.dist-info/LICENSE
cell_stamp-0.1.2.dist-info/METADATA
cell_stamp-0.1.2.dist-info/WHEEL
cell_stamp-0.1.2.dist-info/top_level.txt
cell_stamp-0.1.2.dist-info/RECORD
