Metadata-Version: 2.1
Name: cell-stamp
Version: 0.1.2
Summary: STAMP for genetic perturbation prediction
Home-page: https://github.com/bm2-lab/STAMP
Author: Yicheng Gao, Zhiting Wei, Qi Liu
License: GPL-3.0 license
License-File: LICENSE
Requires-Dist: numpy ==1.24.3
Requires-Dist: pandas ==2.2.2
Requires-Dist: tqdm ==4.66.4
Requires-Dist: scikit-learn ==1.5.0
Requires-Dist: torch
Requires-Dist: scanpy ==1.10.1
Requires-Dist: dcor ==0.6
Requires-Dist: scipy ==1.13.1
Requires-Dist: joblib ==1.4.2
Requires-Dist: pyyaml
Requires-Dist: setuptools ==69.5.1
